qc_openscenario/__init__.py
qc_openscenario/__main__.py
qc_openscenario/basic_preconditions.py
qc_openscenario/checks/__init__.py
qc_openscenario/checks/basic_checker/__init__.py
qc_openscenario/checks/basic_checker/fileheader_is_present.py
qc_openscenario/checks/basic_checker/root_tag_is_openscenario.py
qc_openscenario/checks/basic_checker/valid_xml_document.py
qc_openscenario/checks/basic_checker/version_is_defined.py
qc_openscenario/checks/data_type_checker/__init__.py
qc_openscenario/checks/data_type_checker/allowed_operators.py
qc_openscenario/checks/data_type_checker/non_negative_transition_time_in_light_state_action.py
qc_openscenario/checks/data_type_checker/positive_duration_in_phase.py
qc_openscenario/checks/models.py
qc_openscenario/checks/parameters_checker/__init__.py
qc_openscenario/checks/parameters_checker/valid_parameter_declaration_in_catalogs.py
qc_openscenario/checks/reference_checker/__init__.py
qc_openscenario/checks/reference_checker/resolvable_entity_references.py
qc_openscenario/checks/reference_checker/resolvable_signal_id_in_traffic_signal_state_action.py
qc_openscenario/checks/reference_checker/resolvable_storyboard_element_reference.py
qc_openscenario/checks/reference_checker/resolvable_traffic_signal_controller_by_traffic_signal_controller_ref.py
qc_openscenario/checks/reference_checker/resolvable_variable_reference.py
qc_openscenario/checks/reference_checker/unique_element_names_on_same_level.py
qc_openscenario/checks/reference_checker/uniquely_resolvable_entity_references.py
qc_openscenario/checks/reference_checker/valid_actor_reference_in_private_actions.py
qc_openscenario/checks/schema_checker/__init__.py
qc_openscenario/checks/schema_checker/valid_schema.py
qc_openscenario/checks/utils.py
qc_openscenario/constants.py
qc_openscenario/main.py
qc_openscenario/schema/1.0.0/OpenSCENARIO.xsd
qc_openscenario/schema/1.1.0/OpenSCENARIO.xsd
qc_openscenario/schema/1.1.1/OpenSCENARIO.xsd
qc_openscenario/schema/1.2.0/OpenSCENARIO.xsd
asam_qc_openscenarioxml-1.0.0.dist-info/LICENSE
asam_qc_openscenarioxml-1.0.0.dist-info/LICENSES/3rd_party_terms_and_licenses/Black_LICENSE
asam_qc_openscenarioxml-1.0.0.dist-info/LICENSES/3rd_party_terms_and_licenses/Lxml_LICENSE
asam_qc_openscenarioxml-1.0.0.dist-info/LICENSES/3rd_party_terms_and_licenses/Pytest_LICENSE
asam_qc_openscenarioxml-1.0.0.dist-info/LICENSES/readme.md
asam_qc_openscenarioxml-1.0.0.dist-info/METADATA
asam_qc_openscenarioxml-1.0.0.dist-info/WHEEL
asam_qc_openscenarioxml-1.0.0.dist-info/entry_points.txt
asam_qc_openscenarioxml-1.0.0.dist-info/RECORD
