Metadata-Version: 2.1
Name: asam-qc-openscenarioxml
Version: 1.0.0
Summary: This project implements the OpenScenario Checker for the ASAM Quality Checker project.
License: MPL-2.0
Author: Danilo Romano
Author-email: danilo@ivex.ai
Requires-Python: >=3.10,<4.0
Classifier: License :: OSI Approved
Classifier: Programming Language :: Python :: 3
Classifier: Programming Language :: Python :: 3.10
Classifier: Programming Language :: Python :: 3.11
Classifier: Programming Language :: Python :: 3.12
Classifier: Programming Language :: Python :: 3.13
Requires-Dist: asam-qc-baselib (>=1.0.0rc1,<2.0.0)
Requires-Dist: lxml (>=5.2.2,<6.0.0)
